gym_foo/__init__.py
gym_my_yumi-0.0.1.dist-info/METADATA
gym_my_yumi-0.0.1.dist-info/WHEEL
gym_my_yumi-0.0.1.dist-info/top_level.txt
gym_my_yumi-0.0.1.dist-info/RECORD
